MANIFEST.in
README.md
setup.py
django_niji.egg-info/PKG-INFO
django_niji.egg-info/SOURCES.txt
django_niji.egg-info/dependency_links.txt
django_niji.egg-info/requires.txt
django_niji.egg-info/top_level.txt
docs/Makefile
docs/make.bat
docs/build/doctrees/environment.pickle
docs/build/doctrees/index.doctree
docs/build/html/.buildinfo
docs/build/html/genindex.html
docs/build/html/index.html
docs/build/html/objects.inv
docs/build/html/search.html
docs/build/html/searchindex.js
docs/build/html/_sources/index.txt
docs/build/html/_static/ajax-loader.gif
docs/build/html/_static/alabaster.css
docs/build/html/_static/basic.css
docs/build/html/_static/comment-bright.png
docs/build/html/_static/comment-close.png
docs/build/html/_static/comment.png
docs/build/html/_static/custom.css
docs/build/html/_static/doctools.js
docs/build/html/_static/down-pressed.png
docs/build/html/_static/down.png
docs/build/html/_static/file.png
docs/build/html/_static/jquery-1.11.1.js
docs/build/html/_static/jquery.js
docs/build/html/_static/minus.png
docs/build/html/_static/plus.png
docs/build/html/_static/pygments.css
docs/build/html/_static/searchtools.js
docs/build/html/_static/underscore-1.3.1.js
docs/build/html/_static/underscore.js
docs/build/html/_static/up-pressed.png
docs/build/html/_static/up.png
docs/build/html/_static/websupport.js
docs/source/conf.py
docs/source/index.rst
niji/__init__.py
niji/admin.py
niji/api.py
niji/apps.py
niji/context_processors.py
niji/forms.py
niji/misc.py
niji/models.py
niji/serializers.py
niji/tasks.py
niji/tests.py
niji/urls.py
niji/views.py
niji/management/__init__.py
niji/management/commands/__init__.py
niji/management/commands/rerender.py
niji/migrations/0001_initial.py
niji/migrations/0002_auto_20160126_1209.py
niji/migrations/0003_forumavatar.py
niji/migrations/0004_auto_20160628_0609.py
niji/migrations/0005_topic_closed.py
niji/migrations/__init__.py
niji/static/niji/css/editor.css
niji/static/niji/css/main.css
niji/static/niji/image/bg.jpg
niji/templates/niji/base.html
niji/templates/niji/create_appendix.html
niji/templates/niji/create_topic.html
niji/templates/niji/edit_topic.html
niji/templates/niji/index.html
